<?xml version="1.0" encoding="UTF-8"?>

<!-- Mapper파일을 구성하기 위한 Doctype 설정 -->
<!DOCTYPE mapper 
	PUBLIC "-//mybatis.org//DTD Mapper 3.0//EN"
	"http://mybatis.org/dtd/mybatis-3-mapper.dtd">

<mapper namespace="com.bc.bodycoding.admin.gym.GymService">

	<select id="select"
		parameterType="com.bc.bodycoding.MemberDTO"
		resultType="com.bc.bodycoding.MemberDTO">
		select * from member where mem_type like '%ADMIN%'
	</select>
	
	<insert id="insert"
		parameterType="com.bc.bodycoding.admin.gym.GymDTO">
		insert into GYM_DETAIL (gym_code, gym_scale, gym_dtail_img, 
			facility_parking, facility_health, facility_yoga, facility_gx, 
			facility_pilates, facility_pt, facility_24hour, facility_shower, 
			facility_wear, facility_locker, rtime_week_start, rtime_week_end, 
			rtime_sat_start, rtime_sat_end, rtime_holy_start, rtime_holy_end) 
		values(#{gym_code}, #{gym_scale}, #{gym_dtail_img}, #{facility_parking},
		 #{facility_health}, #{facility_yoga}, #{facility_gx}, #{facility_pilates},
		  #{facility_pt}, #{facility_24hour}, #{facility_shower}, #{facility_wear}, 
		  #{facility_locker}, #{rtime_week_start}, #{rtime_week_end},
		  #{rtime_sat_start}, #{rtime_sat_end}, #{rtime_holy_start},
		  #{rtime_holy_end})
	</insert>
	
	<select id="selectOne"
		parameterType="com.bc.bodycoding.admin.gym.GymDTO"
		resultType="com.bc.bodycoding.admin.gym.GymDTO">
		select * from GYM_DETAIL where gym_code=#{gym_code}
	</select>
	
	<update id="update"
		parameterType="com.bc.bodycoding.admin.gym.GymDTO">
		update GYM_DETAIL set gym_scale=#{gym_scale}, gym_dtail_img=#{gym_dtail_img}, 
			facility_parking=#{facility_parking}, facility_health=#{facility_health}, facility_yoga=#{facility_yoga}, facility_gx=#{facility_gx}, 
			facility_pilates=#{facility_pilates}, facility_pt=#{facility_pt}, facility_24hour=#{facility_24hour}, facility_shower=#{facility_shower}, 
			facility_wear=#{facility_wear}, facility_locker=#{facility_locker}, rtime_week_start=#{rtime_week_start}, rtime_week_end=#{rtime_week_end}, 
			rtime_sat_start=#{rtime_sat_start}, rtime_sat_end=#{rtime_sat_end}, rtime_holy_start=#{rtime_holy_start}, rtime_holy_end=#{rtime_holy_end} 
		where gym_code=#{gym_code}
	</update>
	
	<delete id="delete"
		parameterType="com.bc.bodycoding.admin.gym.GymDTO">
		delete from GYM_DETAIL where gym_code=#{gym_code}
	</delete>
	
	<insert id="insertMemberASUB"
		parameterType="com.bc.bodycoding.MemberDTO">
		insert into MEMBER (mem_id, mem_pass, mem_name, 
			mem_phone, mem_address, mem_type, mem_status, 
			gym_code,  mem_comment, mem_img)
    	values (#{mem_id}, #{mem_pass}, #{mem_name},
    		#{mem_phone}, #{mem_address}, #{mem_type}, #{mem_status},
    		#{gym_code}, #{mem_comment}, #{mem_img})
	</insert>
</mapper>